{
	"type": "flyingfamiliars:brazier",
	"inputItems": [
		{
			"item": "flyingfamiliars:phylactery_green"
		},
		{
			"item": "minecraft:mushroom_stew"
		},
		{
			"item": "flyingfamiliars:eye_of_the_storm"
		},
		{
			"item": "minecraft:mushroom_stew"
		},
		{
			"item": "flyingfamiliars:phylactery_green"
		}
	],
	"inputEntities": [
		{
			"string": "minecraft:mooshroom"
		},
		{
			"string": "minecraft:creeper"
		},
		{
			"string": "minecraft:mooshroom"
		}
	],
	"outputItem": {
		"item": "flyingfamiliars:phylactery_yellow"
	},
	"outputEntity": {
		"string": "minecraft:skeleton_horse"
	}
}